dj_image_finder/__init__.py
dj_image_finder/sample.jpg
dj_image_finder/sample.png
dj_image_finder-0.1.0.dist-info/METADATA
dj_image_finder-0.1.0.dist-info/WHEEL
dj_image_finder-0.1.0.dist-info/entry_points.txt
dj_image_finder-0.1.0.dist-info/RECORD
