Metadata-Version: 2.1
Name: dj-image-finder
Version: 0.1.0
Summary: 
Author: dongjin2008
Author-email: dkim@icsparis.fr
Requires-Python: >=3.10,<4.0
Classifier: Programming Language :: Python :: 3
Classifier: Programming Language :: Python :: 3.10
Classifier: Programming Language :: Python :: 3.11
Requires-Dist: click (>=8.1.3,<9.0.0)
Requires-Dist: climage (>=0.1.3,<0.2.0)
Requires-Dist: getkey (>=0.6.5,<0.7.0)
Requires-Dist: google-search-results (>=2.4.1,<3.0.0)
Requires-Dist: keyboard (>=0.13.5,<0.14.0)
